{
  "Cresselia": {"Trick Room Setter": {"moves": ["Trick Room", "Moonblast", "Lunar Dance", ["Shadow Ball", "Moonlight"]], "item": "Colbur Berry", "nature": "Relaxed", "ivs": {"atk": 0, "spe": 0}, "evs": {"hp": 248, "def": 84, "spd": 176}}},
  "Venusaur": {"Chlorophyll Sweeper": {"moves": ["Growth", "Giga Drain", "Weather Ball", "Sludge Bomb"], "ability": "Chlorophyll", "item": "Life Orb", "nature": "Modest", "evs": {"spa": 252, "spd": 4, "spe": 252}}},
  "Nidoqueen": {"Offensive Stealth Rock": {"moves": ["Stealth Rock", "Earth Power", "Sludge Wave", "Fire Blast"], "ability": "Sheer Force", "item": "Life Orb", "nature": "Modest", "evs": {"hp": 120, "spa": 252, "spe": 136}}},
  "Nidoking": {"Wallbreaker": {"moves": ["Sludge Wave", "Earth Power", "Fire Blast", ["Thunderbolt", "Substitute"]], "ability": "Sheer Force", "item": "Life Orb", "nature": "Modest", "evs": {"spa": 252, "spd": 4, "spe": 252}}},
  "Tentacruel": {"Defensive Spinner": {"moves": ["Scald", "Sludge Bomb", "Knock Off", "Rapid Spin"], "ability": "Liquid Ooze", "item": "Black Sludge", "nature": "Timid", "evs": {"hp": 252, "def": 96, "spe": 160}}},
  "Slowbro-Galar": {"Calm Mind": {"moves": ["Calm Mind", ["Sludge Bomb", "Psyshock"], ["Scald", "Flamethrower"], "Slack Off"], "ability": "Regenerator", "item": ["Colbur Berry", "Shuca Berry"], "nature": "Bold", "evs": {"hp": 252, "def": 252, "spd": 4}}, "Assault Vest": {"moves": ["Shell Side Arm", ["Future Sight", "Ice Beam", "Scald"], "Psyshock", "Flamethrower"], "ability": "Regenerator", "item": "Assault Vest", "nature": "Quiet", "evs": {"hp": 252, "spa": 16, "spd": 240}}},
  "Magneton": {"Choice Specs Trapper": {"moves": ["Thunderbolt", "Volt Switch", "Flash Cannon", "Steel Beam"], "item": "Choice Specs", "nature": "Modest", "evs": {"spa": 252, "spd": 4, "spe": 252}}},
  "Cloyster": {"Shell Smash Sweeper": {"moves": ["Shell Smash", "Icicle Spear", ["Pin Missile", "Poison Jab"], "Hydro Pump"], "ability": "Skill Link", "item": ["Life Orb", "White Herb"], "nature": "Naughty", "evs": {"atk": 252, "spa": 4, "spe": 252}}},
  "Marowak-Alola": {"Trick Room Wallbreaker": {"moves": ["Flare Blitz", "Poltergeist", "Substitute", ["Shadow Bone", "Bonemerang"]], "ability": "Rock Head", "item": "Thick Club", "nature": "Adamant", "evs": {"hp": 248, "atk": 252, "def": 8}}},
  "Chansey": {"Defensive": {"moves": ["Seismic Toss", ["Toxic", "Thunder Wave"], "Soft-Boiled", ["Teleport", "Stealth Rock", "Aromatherapy"]], "item": "Eviolite", "nature": "Bold", "evs": {"hp": 252, "def": 252, "spd": 4}}},
  "Starmie": {"Offensive": {"moves": ["Hydro Pump", "Ice Beam", "Thunderbolt", "Recover"], "ability": "Analytic", "item": "Life Orb", "nature": "Timid", "evs": {"spa": 252, "spd": 4, "spe": 252}}},
  "Gyarados": {"Dragon Dance Sweeper": {"moves": ["Dragon Dance", "Waterfall", "Ice Fang", "Power Whip"], "ability": "Moxie", "item": ["Mystic Water", "Lum Berry", "Heavy-Duty Boots"], "nature": "Adamant", "evs": {"atk": 252, "spd": 4, "spe": 252}}, "Substitute + Dragon Dance": {"moves": ["Substitute", "Dragon Dance", "Waterfall", "Bounce"], "ability": "Moxie", "item": "Leftovers", "nature": "Adamant", "evs": {"atk": 252, "spd": 4, "spe": 252}}},
  "Ditto": {"Imposter": {"moves": ["Transform"], "ability": "Imposter", "item": "Choice Scarf", "nature": "Quiet", "ivs": {"spe": 0}, "evs": {"hp": 252, "def": 4, "spa": 252}}},
  "Articuno": {"Specially Defensive": {"moves": ["Freeze-Dry", "Defog", "Heal Bell", "Roost"], "item": "Heavy-Duty Boots", "nature": "Calm", "evs": {"hp": 248, "spd": 204, "spe": 56}}},
  "Moltres": {"Offensive": {"moves": ["Flamethrower", "Hurricane", "U-turn", "Roost"], "ability": "Flame Body", "item": "Heavy-Duty Boots", "nature": "Timid", "evs": {"spa": 252, "spd": 4, "spe": 252}}, "Support": {"moves": ["Mystical Fire", "Toxic", "U-turn", "Roost"], "ability": "Flame Body", "item": "Heavy-Duty Boots", "nature": "Timid", "evs": {"hp": 252, "def": 4, "spe": 252}}},
  "Crobat": {"Offensive Pivot": {"moves": ["Brave Bird", "U-turn", "Roost", "Taunt"], "item": "Heavy-Duty Boots", "nature": "Jolly", "evs": {"hp": 108, "atk": 148, "spe": 252}}},
  "Lanturn": {"Cleric Support": {"moves": [["Volt Switch", "Thunderbolt"], "Scald", "Heal Bell", "Toxic"], "item": "Leftovers", "nature": "Calm", "evs": {"hp": 252, "spd": 132, "spe": 124}}},
  "Azumarill": {"Choice Band": {"moves": ["Liquidation", "Play Rough", "Aqua Jet", ["Ice Punch", "Knock Off"]], "ability": "Huge Power", "item": "Choice Band", "nature": "Adamant", "evs": {"atk": 252, "spd": 4, "spe": 252}}, "Belly Drum": {"moves": ["Belly Drum", "Aqua Jet", "Play Rough", "Knock Off"], "ability": "Huge Power", "item": "Sitrus Berry", "nature": "Adamant", "evs": {"hp": 4, "atk": 252, "spe": 252}}},
  "Politoed": {"Rain Setter": {"moves": ["Scald", "Encore", ["Ice Beam", "Toxic"], "Rest"], "ability": "Drizzle", "item": "Damp Rock", "nature": "Bold", "evs": {"hp": 248, "def": 252, "spd": 8}}},
  "Quagsire": {"Unaware Wall": {"moves": ["Scald", "Earthquake", "Toxic", "Recover"], "ability": "Unaware", "item": "Leftovers", "nature": "Relaxed", "evs": {"hp": 252, "def": 220, "spd": 36}}},
  "Umbreon": {"Physically Defensive": {"moves": ["Foul Play", "Toxic", "Wish", "Protect"], "ability": "Inner Focus", "item": "Leftovers", "nature": "Bold", "evs": {"hp": 252, "def": 252, "spd": 4}}},
  "Slowking": {"Defensive Pivot": {"moves": ["Scald", ["Psychic", "Future Sight"], "Slack Off", "Teleport"], "ability": "Regenerator", "item": ["Colbur Berry", "Heavy-Duty Boots"], "nature": "Relaxed", "ivs": {"atk": 0, "spe": 0}, "evs": {"hp": 248, "def": 252, "spd": 8}}, "Calm Mind": {"moves": ["Scald", "Psyshock", "Calm Mind", "Slack Off"], "ability": "Regenerator", "item": "Colbur Berry", "nature": "Bold", "evs": {"hp": 252, "def": 252, "spd": 4}}},
  "Scizor": {"3 Attacks + Roost": {"moves": ["Bullet Punch", "U-turn", "Knock Off", "Roost"], "ability": "Technician", "item": "Heavy-Duty Boots", "nature": "Adamant", "evs": {"hp": 248, "atk": 16, "def": 104, "spd": 140}}, "Bulky Swords Dance": {"moves": ["Swords Dance", "Bullet Punch", ["Knock Off", "U-turn"], "Roost"], "ability": "Technician", "item": "Heavy-Duty Boots", "nature": "Adamant", "evs": {"hp": 248, "atk": 16, "def": 244}}, "Offensive Swords Dance": {"moves": ["Swords Dance", "Bullet Punch", ["Knock Off", "Quick Attack"], ["Dual Wingbeat", "Superpower", "Bug Bite"]], "ability": "Technician", "item": "Life Orb", "nature": "Adamant", "evs": {"atk": 252, "spd": 4, "spe": 252}}},
  "Mantine": {"Rain Sweeper": {"moves": ["Scald", "Hurricane", "Substitute", "Roost"], "item": "Heavy-Duty Boots", "nature": "Modest", "evs": {"def": 40, "spa": 216, "spe": 252}}},
  "Skarmory": {"Iron Defense": {"moves": ["Iron Defense", "Body Press", "Roost", ["Spikes", "Defog"]], "ability": "Sturdy", "item": ["Rocky Helmet", "Safety Goggles"], "nature": "Bold", "evs": {"hp": 252, "def": 160, "spe": 96}}, "Physical Wall": {"moves": [["Body Press", "Brave Bird"], "Spikes", "Roost", ["Toxic", "Whirlwind"]], "ability": "Sturdy", "item": "Rocky Helmet", "nature": "Impish", "evs": {"hp": 252, "def": 160, "spe": 96}}},
  "Kingdra": {"Choice Specs": {"moves": ["Hydro Pump", "Draco Meteor", "Hurricane", "Surf"], "item": "Choice Specs", "nature": "Modest", "evs": {"def": 4, "spa": 252, "spe": 252}}},
  "Porygon2": {"Trick Room Setter": {"moves": ["Trick Room", "Foul Play", "Recover", "Teleport"], "item": "Eviolite", "nature": "Sassy", "ivs": {"atk": 0, "spe": 0}, "evs": {"hp": 248, "def": 44, "spd": 216}}},
  "Raikou": {"Offensive Pivot": {"moves": ["Volt Switch", "Thunderbolt", "Scald", "Aura Sphere"], "ability": "Inner Focus", "item": "Heavy-Duty Boots", "nature": "Timid", "ivs": {"atk": 0}, "evs": {"spa": 252, "spd": 4, "spe": 252}}},
  "Entei": {"Wallbreaker": {"moves": ["Sacred Fire", "Flare Blitz", "Stone Edge", "Extreme Speed"], "ability": "Inner Focus", "item": "Choice Band", "nature": "Jolly", "evs": {"atk": 252, "spd": 4, "spe": 252}}},
  "Suicune": {"CroCune": {"moves": ["Calm Mind", "Scald", "Rest", "Sleep Talk"], "item": "Leftovers", "nature": "Bold", "evs": {"hp": 252, "def": 252, "spd": 4}}},
  "Swampert": {"Mixed Wall": {"moves": ["Earthquake", "Flip Turn", ["Toxic", "Yawn"], "Stealth Rock"], "item": "Leftovers", "nature": "Sassy", "evs": {"hp": 252, "def": 144, "spd": 112}}},
  "Torkoal": {"Sun Setter": {"moves": ["Stealth Rock", "Lava Plume", "Rapid Spin", ["Toxic", "Yawn"]], "ability": "Drought", "item": "Heat Rock", "nature": "Bold", "evs": {"hp": 248, "def": 252, "spd": 8}}},
  "Flygon": {"Defog": {"moves": ["Earth Power", "Flamethrower", "Defog", "Roost"], "item": "Leftovers", "nature": "Timid", "evs": {"spa": 128, "spd": 128, "spe": 252}}},
  "Crawdaunt": {"Choice Band": {"moves": ["Crabhammer", "Knock Off", "Aqua Jet", ["Close Combat", "Lash Out"]], "ability": "Adaptability", "item": "Choice Band", "nature": "Adamant", "evs": {"atk": 252, "def": 4, "spe": 252}}},
  "Salamence": {"Special Attacker": {"moves": [["Draco Meteor", "Defog"], ["Hurricane", "Defog"], "Flamethrower", "Roost"], "item": "Heavy-Duty Boots", "nature": "Timid", "evs": {"spa": 252, "spd": 4, "spe": 252}}, "Dragon Dance": {"moves": ["Dragon Dance", "Outrage", "Dual Wingbeat", ["Earthquake", "Fire Blast"]], "ability": "Moxie", "item": ["Heavy-Duty Boots", "Life Orb"], "nature": ["Jolly", "Naive"], "evs": {"atk": 252, "spd": 4, "spe": 252}}, "Defensive": {"moves": [["Dual Wingbeat", "Toxic"], "Flamethrower", "Roost", "Defog"], "item": "Heavy-Duty Boots", "nature": "Impish", "evs": {"hp": 252, "def": 160, "spe": 96}}},
  "Registeel": {"Demon Registeel (Double Dance)": {"moves": ["Amnesia", "Iron Defense", "Rest", "Body Press"], "item": "Chesto Berry", "nature": "Bold", "evs": {"hp": 252, "def": 252, "spd": 4}}, "Stealth Rock": {"moves": [["Seismic Toss", "Body Press"], ["Toxic", "Thunder Wave"], "Earthquake", "Stealth Rock"], "item": "Leftovers", "nature": "Careful", "evs": {"hp": 252, "def": 4, "spd": 252}}},
  "Jirachi": {"Choice Scarf": {"moves": ["Iron Head", "U-turn", ["Trick", "Ice Punch"], "Healing Wish"], "item": "Choice Scarf", "nature": "Jolly", "evs": {"atk": 252, "spd": 4, "spe": 252}}, "SubToxic": {"moves": ["Substitute", "Iron Head", "Fire Punch", "Toxic"], "item": "Leftovers", "nature": "Jolly", "evs": {"hp": 252, "atk": 4, "spe": 252}}, "Wish + Protect": {"moves": ["Wish", "Protect", "Iron Head", "U-turn"], "item": "Leftovers", "nature": "Jolly", "evs": {"hp": 252, "spd": 16, "spe": 240}}},
  "Roserade": {"Spikes": {"moves": ["Giga Drain", "Sludge Bomb", "Spikes", ["Sleep Powder", "Synthesis"]], "item": "Black Sludge", "nature": "Timid", "evs": {"hp": 248, "def": 8, "spe": 252}}},
  "Gastrodon": {"Mixed Wall": {"moves": [["Scald", "Ice Beam"], "Earthquake", "Recover", "Toxic"], "ability": "Storm Drain", "item": ["Heavy-Duty Boots", "Leftovers"], "nature": "Sassy", "evs": {"hp": 252, "def": 84, "spd": 172}}},
  "Hippowdon": {"Stealth Rock": {"moves": ["Stealth Rock", "Earthquake", "Toxic", "Slack Off"], "item": ["Leftovers", "Rocky Helmet"], "nature": "Impish", "evs": {"hp": 252, "atk": 8, "def": 32, "spd": 216}}},
  "Rhyperior": {"Stealth Rock": {"moves": ["Stone Edge", "Earthquake", "Stealth Rock", ["Toxic", "Heat Crash"]], "ability": "Solid Rock", "item": "Leftovers", "nature": "Careful", "evs": {"hp": 252, "atk": 4, "spd": 252}}},
  "Tangrowth": {"Assault Vest": {"moves": ["Power Whip", "Knock Off", "Sludge Bomb", "Focus Blast"], "ability": "Regenerator", "item": "Assault Vest", "nature": "Relaxed", "evs": {"hp": 252, "def": 96, "spd": 160}}, "Physically Defensive": {"moves": [["Giga Drain", "Power Whip"], "Knock Off", ["Sludge Bomb", "Focus Blast"], ["Sleep Powder", "Synthesis"]], "ability": "Regenerator", "item": "Rocky Helmet", "nature": "Relaxed", "evs": {"hp": 252, "def": 252, "spd": 4}}},
  "Togekiss": {"Nasty Plot": {"moves": ["Nasty Plot", "Air Slash", ["Heal Bell", "Thunder Wave"], "Roost"], "ability": "Serene Grace", "item": "Heavy-Duty Boots", "nature": "Timid", "evs": {"hp": 248, "spd": 8, "spe": 252}}},
  "Mamoswine": {"Wallbreaker": {"moves": ["Icicle Crash", "Earthquake", "Ice Shard", "Knock Off"], "item": ["Life Orb", "Never-Melt Ice"], "nature": "Adamant", "evs": {"atk": 252, "spd": 4, "spe": 252}}},
  "Froslass": {"Suicide Lead": {"moves": ["Spikes", "Poltergeist", "Taunt", "Destiny Bond"], "ability": "Cursed Body", "item": "Focus Sash", "nature": "Jolly", "evs": {"hp": 248, "atk": 8, "spe": 252}}},
  "Rotom-Heat": {"Pivot": {"moves": ["Overheat", "Volt Switch", "Toxic", "Pain Split"], "item": "Heavy-Duty Boots", "nature": "Timid", "evs": {"hp": 252, "def": 104, "spe": 152}}},
  "Rotom-Wash": {"Pivot": {"moves": ["Volt Switch", "Hydro Pump", "Pain Split", ["Will-O-Wisp", "Defog"]], "item": "Leftovers", "nature": "Bold", "evs": {"hp": 248, "def": 172, "spe": 88}}, "Choice Scarf": {"moves": ["Volt Switch", "Hydro Pump", ["Defog", "Pain Split"], "Trick"], "item": "Choice Scarf", "nature": "Timid", "evs": {"hp": 252, "spd": 4, "spe": 252}}},
  "Azelf": {"Pivot": {"moves": ["Psychic", "Flamethrower", "U-turn", ["Energy Ball", "Knock Off"]], "item": ["Expert Belt", "Heavy-Duty Boots"], "nature": "Timid", "evs": {"def": 4, "spa": 252, "spe": 252}}, "Nasty Plot": {"moves": ["Nasty Plot", "Psyshock", "Fire Blast", ["Energy Ball", "Dazzling Gleam"]], "item": ["Expert Belt", "Life Orb"], "nature": "Timid", "evs": {"def": 4, "spa": 252, "spe": 252}}},
  "Excadrill": {"Utility": {"moves": ["Earthquake", "Iron Head", "Rapid Spin", ["Toxic", "Stealth Rock"]], "ability": "Mold Breaker", "item": "Leftovers", "nature": "Jolly", "evs": {"atk": 252, "spd": 4, "spe": 252}}, "Suicide Lead": {"moves": ["Stealth Rock", "Earthquake", "Rapid Spin", "Rock Tomb"], "ability": "Mold Breaker", "item": "Focus Sash", "nature": "Jolly", "evs": {"atk": 252, "spd": 4, "spe": 252}}, "Swords Dance": {"moves": ["Earthquake", "Iron Head", "Rapid Spin", "Swords Dance"], "ability": "Mold Breaker", "item": "Leftovers", "nature": "Jolly", "evs": {"atk": 252, "spd": 4, "spe": 252}}},
  "Conkeldurr": {"Guts Wallbreaker": {"moves": [["Drain Punch", "Close Combat"], ["Facade", "Ice Punch"], "Knock Off", "Mach Punch"], "item": "Flame Orb", "nature": "Adamant", "evs": {"atk": 252, "spd": 4, "spe": 252}}},
  "Seismitoad": {"Defensive Stealth Rock": {"moves": ["Stealth Rock", "Scald", "Knock Off", "Toxic"], "ability": "Water Absorb", "item": "Leftovers", "nature": "Bold", "evs": {"hp": 252, "def": 192, "spe": 64}}},
  "Scolipede": {"Suicide Lead": {"moves": ["Spikes", "Poison Jab", "Endeavor", "Earthquake"], "ability": "Speed Boost", "item": "Focus Sash", "nature": "Jolly", "evs": {"atk": 252, "spd": 4, "spe": 252}}},
  "Krookodile": {"Stealth Rock": {"moves": ["Earthquake", "Knock Off", "Stealth Rock", ["Taunt", "Toxic"]], "item": ["Leftovers", "Rocky Helmet", "Chople Berry"], "nature": "Jolly", "evs": {"hp": 80, "def": 204, "spe": 224}}},
  "Darmanitan": {"Choice Scarf": {"moves": ["Flare Blitz", "U-turn", "Rock Slide", "Earthquake"], "item": "Choice Scarf", "nature": "Jolly", "evs": {"atk": 252, "spd": 4, "spe": 252}}},
  "Sigilyph": {"Offensive Defog": {"moves": ["Psyshock", "Heat Wave", "Roost", "Defog"], "ability": "Magic Guard", "item": "Life Orb", "nature": "Timid", "evs": {"spa": 252, "spd": 4, "spe": 252}}},
  "Reuniclus": {"Life Orb + 3 Attacks": {"moves": ["Psychic", "Thunder", "Focus Blast", "Recover"], "ability": "Magic Guard", "item": "Life Orb", "nature": "Modest", "evs": {"hp": 188, "def": 32, "spa": 252, "spd": 36}}},
  "Vanilluxe": {"Choice Specs": {"moves": ["Blizzard", "Freeze-Dry", "Sleep Talk"], "ability": "Snow Warning", "item": "Choice Specs", "nature": "Modest", "evs": {"hp": 4, "spa": 252, "spe": 252}}},
  "Amoonguss": {"Defensive": {"moves": [["Spore", "Stun Spore"], ["Giga Drain", "Synthesis"], "Sludge Bomb", "Foul Play"], "ability": "Regenerator", "item": ["Rocky Helmet", "Black Sludge"], "nature": "Bold", "evs": {"hp": 252, "def": 220, "spd": 36}}},
  "Jellicent": {"Defensive Utility": {"moves": [["Hex", "Night Shade"], "Taunt", "Will-O-Wisp", "Recover"], "ability": ["Cursed Body", "Water Absorb"], "item": ["Heavy-Duty Boots", "Colbur Berry"], "nature": "Bold", "evs": {"hp": 252, "def": 56, "spe": 200}}},
  "Chandelure": {"Hex": {"moves": ["Flamethrower", "Hex", ["Toxic", "Will-O-Wisp"], ["Protect", "Taunt"]], "ability": "Flame Body", "item": "Heavy-Duty Boots", "nature": "Timid", "evs": {"spa": 252, "spd": 4, "spe": 252}}, "Choice Specs": {"moves": ["Fire Blast", "Shadow Ball", "Flamethrower", ["Sleep Talk", "Trick"]], "ability": "Flame Body", "item": "Choice Specs", "nature": "Timid", "evs": {"spa": 252, "spd": 4, "spe": 252}}},
  "Haxorus": {"Swords Dance": {"moves": ["Swords Dance", "Scale Shot", "Close Combat", "Poison Jab"], "ability": "Mold Breaker", "item": ["Life Orb", "Lum Berry"], "nature": "Jolly", "evs": {"atk": 252, "spd": 4, "spe": 252}}},
  "Mandibuzz": {"Physically Defensive": {"moves": ["Foul Play", ["Knock Off", "Defog"], "U-turn", "Roost"], "ability": "Overcoat", "item": "Heavy-Duty Boots", "nature": "Impish", "evs": {"hp": 248, "def": 164, "spe": 96}}},
  "Durant": {"All-out Attacker": {"moves": ["First Impression", "Iron Head", "Rock Slide", "Superpower"], "ability": "Hustle", "item": ["Life Orb", "Choice Band"], "nature": "Jolly", "evs": {"atk": 252, "spd": 4, "spe": 252}}},
  "Hydreigon": {"Choice Specs": {"moves": ["Draco Meteor", "Dark Pulse", "Flamethrower", ["Roost", "U-turn"]], "item": "Choice Specs", "nature": "Timid", "evs": {"spa": 252, "spd": 4, "spe": 252}}, "Choice Scarf": {"moves": ["Draco Meteor", "Dark Pulse", "U-turn", ["Fire Blast", "Defog", "Roost"]], "item": "Choice Scarf", "nature": ["Timid", "Modest"], "evs": {"spa": 252, "spd": 4, "spe": 252}}, "Dragon Dance": {"moves": ["Dragon Dance", "Crunch", "Scale Shot", "Fire Blast"], "item": "Life Orb", "nature": "Naive", "evs": {"atk": 252, "spa": 4, "spe": 252}}},
  "Cobalion": {"Wallbreaker": {"moves": ["Swords Dance", "Close Combat", ["Stone Edge", "Iron Head"], "Megahorn"], "item": ["Leftovers", "Rocky Helmet", "Shuca Berry"], "nature": "Jolly", "evs": {"atk": 252, "spd": 4, "spe": 252}}, "Utility": {"moves": ["Stealth Rock", "Close Combat", ["Iron Head", "Toxic"], ["Swords Dance", "Volt Switch", "Taunt"]], "item": ["Rocky Helmet", "Leftovers"], "nature": "Jolly", "evs": {"atk": 252, "spd": 4, "spe": 252}}},
  "Tornadus": {"Mixed Offensive Pivot": {"moves": ["Acrobatics", "U-turn", "Knock Off", "Heat Wave"], "ability": "Defiant", "nature": "Naive", "evs": {"atk": 252, "spa": 4, "spe": 252}}, "Choice Specs": {"moves": ["Hurricane", "Knock Off", "U-turn", ["Focus Blast", "Weather Ball"]], "ability": "Defiant", "item": "Choice Specs", "nature": "Timid", "evs": {"spa": 252, "spd": 4, "spe": 252}}},
  "Thundurus-Therian": {"Pivot": {"moves": [["Volt Switch", "U-turn"], "Psychic", "Grass Knot", ["Focus Blast", "Knock Off", "Thunderbolt"]], "item": "Heavy-Duty Boots", "nature": "Timid", "evs": {"def": 4, "spa": 252, "spe": 252}}, "Nasty Plot": {"moves": ["Nasty Plot", "Thunderbolt", "Psychic", "Focus Blast"], "item": "Heavy-Duty Boots", "nature": "Timid", "evs": {"def": 4, "spa": 252, "spe": 252}}},
  "Keldeo": {"Choice Specs": {"moves": ["Hydro Pump", "Secret Sword", "Scald", ["Icy Wind", "Air Slash"]], "item": "Choice Specs", "nature": "Timid", "evs": {"spa": 252, "spd": 4, "spe": 252}}, "Calm Mind": {"moves": ["Calm Mind", "Scald", "Secret Sword", "Air Slash"], "item": "Leftovers", "nature": "Timid", "evs": {"spa": 252, "spd": 4, "spe": 252}}},
  "Diggersby": {"Choice Scarf": {"moves": ["Body Slam", "Earthquake", "U-turn", ["Knock Off", "Fire Punch"]], "ability": "Huge Power", "item": "Choice Scarf", "nature": ["Jolly", "Adamant"], "evs": {"atk": 252, "spd": 4, "spe": 252}}, "Swords Dance": {"moves": ["Swords Dance", "Quick Attack", "Earthquake", ["Fire Punch", "Mega Kick"]], "ability": "Huge Power", "item": ["Life Orb", "Silk Scarf"], "nature": "Adamant", "evs": {"atk": 252, "spd": 4, "spe": 252}}},
  "Heliolisk": {"Wallbreaker": {"moves": ["Volt Switch", "Thunder", "Hyper Voice", ["Grass Knot", "Surf"]], "item": "Life Orb", "nature": "Timid", "evs": {"spa": 252, "spd": 4, "spe": 252}}},
  "Noivern": {"Offensive Pivot": {"moves": [["Draco Meteor", "Hurricane"], "Flamethrower", "U-turn", "Roost"], "ability": "Infiltrator", "item": "Heavy-Duty Boots", "nature": "Timid", "evs": {"spa": 252, "spd": 4, "spe": 252}}},
  "Zygarde-10%": {"Choice Band": {"moves": ["Thousand Arrows", "Extreme Speed", "Outrage", ["Superpower", "Toxic"]], "item": "Choice Band", "nature": "Jolly", "evs": {"atk": 252, "spd": 4, "spe": 252}}},
  "Primarina": {"RestTalk": {"moves": ["Scald", "Moonblast", "Rest", "Sleep Talk"], "item": "Leftovers", "nature": "Bold", "evs": {"hp": 252, "def": 252, "spd": 4}}, "3 Attacks": {"moves": ["Scald", "Moonblast", "Ice Beam", ["Substitute", "Protect", "Calm Mind"]], "item": ["Leftovers", "Rindo Berry"], "nature": "Modest", "evs": {"hp": 212, "spa": 160, "spe": 136}}, "Choice Specs": {"moves": ["Hydro Pump", "Moonblast", "Ice Beam", "Scald"], "item": "Choice Specs", "nature": "Modest", "evs": {"hp": 4, "spa": 252, "spe": 252}}},
  "Ribombee": {"Lead": {"moves": ["Sticky Web", "Moonblast", "Stun Spore", ["U-turn", "Skill Swap"]], "ability": "Shield Dust", "item": "Focus Sash", "nature": "Timid", "evs": {"spa": 252, "spd": 4, "spe": 252}}},
  "Lycanroc-Dusk": {"All-out Attacker": {"moves": ["Stone Edge", "Close Combat", "Psychic Fangs", "Accelerock"], "item": ["Choice Band", "Life Orb"], "nature": "Jolly", "evs": {"atk": 252, "spd": 4, "spe": 252}}},
  "Salazzle": {"Offensive": {"moves": ["Flamethrower", "Sludge Wave", "Toxic", "Knock Off"], "item": "Heavy-Duty Boots", "nature": "Timid", "evs": {"spa": 252, "spd": 4, "spe": 252}}},
  "Golisopod": {"Spikes": {"moves": ["First Impression", "Liquidation", "Knock Off", "Spikes"], "item": "Heavy-Duty Boots", "nature": "Adamant", "evs": {"hp": 196, "atk": 252, "spe": 60}}},
  "Dhelmise": {"Spinblocker": {"moves": ["Power Whip", "Poltergeist", "Rapid Spin", "Synthesis"], "item": "Heavy-Duty Boots", "nature": "Careful", "evs": {"hp": 252, "atk": 12, "spd": 136, "spe": 108}}},
  "Tapu Bulu": {"Swords Dance": {"moves": ["Swords Dance", "Horn Leech", "Stone Edge", "Zen Headbutt"], "item": "Life Orb", "nature": ["Adamant", "Jolly"], "evs": {"atk": 252, "spd": 4, "spe": 252}}, "Defensive": {"moves": ["Horn Leech", "Dazzling Gleam", "Toxic", "Synthesis"], "item": "Heavy-Duty Boots", "nature": "Impish", "evs": {"hp": 252, "def": 120, "spe": 136}}},
  "Nihilego": {"Stealth Rock Utility": {"moves": ["Stealth Rock", "Power Gem", "Sludge Bomb", ["Grass Knot", "Knock Off"]], "item": "Black Sludge", "nature": "Timid", "evs": {"def": 80, "spa": 176, "spe": 252}}, "Meteor Beam Sweeper": {"moves": ["Meteor Beam", "Sludge Wave", ["Thunderbolt", "Power Gem"], "Grass Knot"], "item": "Power Herb", "nature": "Timid", "evs": {"def": 80, "spa": 176, "spe": 252}}},
  "Celesteela": {"Defensive": {"moves": ["Heavy Slam", "Flamethrower", "Leech Seed", ["Toxic", "Protect"]], "item": "Leftovers", "nature": "Sassy", "evs": {"hp": 252, "def": 4, "spd": 252}}, "Autotomize": {"moves": ["Autotomize", "Air Slash", "Fire Blast", "Meteor Beam"], "item": "Power Herb", "nature": "Modest", "evs": {"spa": 252, "spd": 4, "spe": 252}}},
  "Necrozma": {"Dragon Dance": {"moves": ["Dragon Dance", "Photon Geyser", "X-Scissor", "Heat Wave"], "item": ["Lum Berry", "Weakness Policy"], "nature": "Naughty", "evs": {"atk": 252, "spa": 4, "spe": 252}}, "Meteor Beam": {"moves": ["Meteor Beam", "Photon Geyser", "Heat Wave", ["Autotomize", "Stealth Rock"]], "item": "Power Herb", "nature": "Modest", "evs": {"hp": 4, "spa": 252, "spe": 252}}, "Calm Mind": {"moves": ["Calm Mind", "Photon Geyser", "Heat Wave", "Moonlight"], "item": "Colbur Berry", "nature": "Bold", "evs": {"hp": 252, "def": 72, "spa": 156, "spe": 28}}},
  "Toxtricity": {"Offensive": {"moves": ["Overdrive", "Boomburst", "Volt Switch", ["Shift Gear", "Sleep Talk", "Sludge Wave"]], "item": ["Silk Scarf", "Air Balloon", "Heavy-Duty Boots"], "nature": "Modest", "evs": {"spa": 252, "spd": 4, "spe": 252}}},
  "Hatterene": {"Calm Mind": {"moves": ["Calm Mind", "Draining Kiss", ["Psyshock", "Psychic"], "Mystical Fire"], "ability": "Magic Bounce", "item": "Leftovers", "nature": "Bold", "evs": {"hp": 252, "def": 244, "spe": 12}}},
  "Obstagoon": {"RestTalk": {"moves": ["Facade", "Knock Off", "Rest", "Sleep Talk"], "ability": "Guts", "item": "Flame Orb", "nature": "Jolly", "evs": {"atk": 252, "spd": 4, "spe": 252}}},
  "Zarude": {"Offensive Pivot": {"moves": ["Power Whip", "Darkest Lariat", "U-turn", "Jungle Healing"], "item": "Heavy-Duty Boots", "nature": "Jolly", "evs": {"atk": 252, "spd": 4, "spe": 252}}, "Choice Scarf": {"moves": ["Power Whip", "Darkest Lariat", "U-turn", "Close Combat"], "item": "Choice Scarf", "nature": "Jolly", "evs": {"atk": 252, "spd": 4, "spe": 252}}},
  "Zarude-Dada": {"Offensive Pivot": {"moves": ["Power Whip", "Darkest Lariat", "U-turn", "Jungle Healing"], "item": "Heavy-Duty Boots", "nature": "Jolly", "evs": {"atk": 252, "spd": 4, "spe": 252}}, "Choice Scarf": {"moves": ["Power Whip", "Darkest Lariat", "U-turn", "Close Combat"], "item": "Choice Scarf", "nature": "Jolly", "evs": {"atk": 252, "spd": 4, "spe": 252}}}
}