{
  "Charizard": {"Dragon Dance (Fire)": {"moves": ["Dragon Dance", "Flare Blitz", "Dragon Claw", ["Earthquake", "Roost"]], "item": "Charizardite X", "nature": "Jolly", "evs": {"atk": 252, "spd": 4, "spe": 252}}, "Drought Wallbreaker (Fire)": {"moves": [["Flamethrower", "Fire Blast"], "Solar Beam", ["Scorching Sands", "Focus Blast"], ["Roost", "Air Slash", "Hidden Power Electric"]], "item": "Charizardite Y", "nature": "Timid", "evs": {"spa": 252, "spd": 4, "spe": 252}}},
  "Ditto": {"Choice Scarf": {"moves": ["Transform"], "ability": "Imposter", "item": "Choice Scarf", "nature": "Relaxed", "ivs": {"spe": 0}, "evs": {"hp": 248, "atk": 8, "def": 252}}},
  "Azumarill": {"Belly Drum (Fairy)": {"moves": ["Belly Drum", "Aqua Jet", "Knock Off", ["Liquidation", "Play Rough"]], "ability": "Huge Power", "item": "Normalium Z", "nature": "Adamant", "evs": {"atk": 252, "spd": 4, "spe": 252}}},
  "Scizor": {"Offensive Swords Dance (Bug)": {"moves": ["Bullet Punch", "Close Combat", "Trailblaze", "Swords Dance"], "ability": "Light Metal", "item": "Scizorite", "nature": "Adamant", "evs": {"hp": 104, "atk": 252, "spe": 152}}},
  "Blissey": {"Specially Defensive (Normal)": {"moves": ["Stealth Rock", "Seismic Toss", ["Teleport", "Toxic", "Thunder Wave"], "Soft-Boiled"], "item": "Heavy-Duty Boots", "nature": "Bold", "evs": {"hp": 252, "def": 252, "spd": 4}}},
  "Sableye": {"Mixed Wall (Dark)": {"moves": ["Knock Off", "Will-O-Wisp", "Recover", ["Protect", "Metal Burst"]], "ability": "Prankster", "item": "Sablenite", "nature": "Careful", "evs": {"hp": 252, "def": 144, "spd": 112}}, "Specially Defensive (Ghost)": {"moves": ["Knock Off", "Will-O-Wisp", "Recover", ["Protect", "Dazzling Gleam", "Metal Burst"]], "ability": "Prankster", "item": "Sablenite", "nature": "Careful", "evs": {"hp": 252, "def": 4, "spd": 252}}},
  "Altaria": {"Offensive Dragon Dance (Dragon)": {"moves": ["Return", "Earthquake", "Dragon Dance", "Roost"], "item": "Altarianite", "nature": "Jolly", "evs": {"hp": 16, "atk": 224, "def": 16, "spe": 252}}},
  "Gastrodon": {"Physically Defensive (Ground)": {"moves": ["Scald", ["Spikes", "Stealth Rock"], ["Toxic", "Earthquake"], "Recover"], "ability": "Storm Drain", "item": ["Leftovers", "Heavy-Duty Boots"], "nature": ["Bold", "Relaxed"], "evs": {"hp": 252, "def": 252, "spd": 4}}},
  "Garchomp": {"Defensive Entry Hazard Setter (Dragon)": {"moves": ["Earthquake", "Stealth Rock", ["Spikes", "Toxic", "Fire Blast"], ["Roar", "Dragon Tail"]], "ability": "Rough Skin", "item": "Rocky Helmet", "nature": "Jolly", "evs": {"hp": 248, "def": 8, "spe": 252}}, "Offensive Entry Hazard Setter (Dragon)": {"moves": [["Stealth Rock", "Spikes"], "Earthquake", "Stone Edge", ["Swords Dance", "Fire Blast"]], "ability": "Rough Skin", "item": "Focus Sash", "nature": ["Jolly", "Naive"], "evs": {"atk": 252, "spd": 4, "spe": 252}}, "Swords Dance (Ground)": {"moves": ["Scale Shot", "Earthquake", ["Fire Fang", "Stone Edge"], "Swords Dance"], "ability": "Rough Skin", "item": ["Firium Z", "Rockium Z"], "nature": "Jolly", "evs": {"atk": 252, "spd": 4, "spe": 252}}},
  "Weavile": {"Choice Scarf (Ice)": {"moves": [["Punishment", "Pursuit"], ["Ice Spinner", "Triple Axel"], "Low Kick", "Knock Off"], "item": "Choice Scarf", "nature": "Jolly", "evs": {"atk": 252, "spd": 4, "spe": 252}, "teratypes": "Dark"}},
  "Gallade": {"Swords Dance (Fighting)": {"moves": [["Triple Axel", "Shadow Sneak", "Knock Off"], "Zen Headbutt", "Close Combat", "Swords Dance"], "ability": "Justified", "item": "Galladite", "nature": "Jolly", "evs": {"atk": 252, "spd": 4, "spe": 252}}},
  "Rotom-Wash": {"Physically Defensive Pivot (Electric)": {"moves": ["Hydro Pump", "Will-O-Wisp", ["Defog", "Pain Split", "Toxic"], "Volt Switch"], "item": "Leftovers", "nature": "Bold", "evs": {"hp": 252, "def": 212, "spe": 44}}},
  "Hydreigon": {"Nasty Plot (Dark)": {"moves": [["Dark Pulse", "Draco Meteor"], "Flamethrower", ["Substitute", "Earth Power"], "Nasty Plot"], "item": ["Leftovers", "Dragonium Z"], "nature": "Timid", "ivs": {"atk": 0}, "evs": {"def": 4, "spa": 252, "spe": 252}}},
  "Volcarona": {"Quiver Dance (Bug)": {"moves": ["Quiver Dance", "Flamethrower", "Psychic", ["Hidden Power Ground", "Giga Drain", "Roost"]], "item": ["Heavy-Duty Boots", "Psychium Z"], "nature": "Timid", "evs": {"spa": 252, "spd": 4, "spe": 252}}, "Quiver Dance (Fire)": {"moves": ["Quiver Dance", "Flamethrower", "Bug Buzz", ["Psychic", "Giga Drain", "Roost"]], "ability": "Swarm", "item": ["Heavy-Duty Boots", "Buginium Z"], "nature": "Timid", "evs": {"spa": 252, "spd": 4, "spe": 252}}},
  "Klefki": {"Dual Screens (Fairy)": {"moves": ["Reflect", "Light Screen", ["Spikes", "Thunder Wave"], "Foul Play"], "item": "Light Clay", "nature": "Bold", "evs": {"hp": 252, "def": 252, "spd": 4}}},
  "Toxapex": {"Physically Defensive (Poison)": {"moves": [["Baneful Bunker", "Toxic", "Toxic Spikes"], "Haze", "Scald", "Recover"], "ability": "Regenerator", "item": "Black Sludge", "nature": "Impish", "evs": {"hp": 252, "def": 252, "spd": 4}}, "Physically Defensive (Water)": {"moves": [["Baneful Bunker", "Toxic", "Toxic Spikes"], ["Haze", "Poison Jab"], "Scald", "Recover"], "ability": "Regenerator", "item": "Black Sludge", "nature": ["Impish", "Relaxed"], "evs": {"hp": 252, "def": 252, "spd": 4}}},
  "Cinderace": {"Swords Dance (Fire)": {"moves": ["Swords Dance", "Pyro Ball", "Giga Impact", ["Gunk Shot", "Sucker Punch"]], "ability": "Libero", "item": "Normalium Z", "nature": "Jolly", "evs": {"atk": 252, "spd": 4, "spe": 252}}},
  "Barraskewda": {"Choice Band (Water)": {"moves": ["Liquidation", ["Psychic Fangs", "Flip Turn"], ["Crunch", "Flip Turn"], "Close Combat"], "item": "Choice Band", "nature": "Adamant", "evs": {"atk": 252, "spd": 4, "spe": 252}}},
  "Meowscarada": {"Choice Scarf (Dark)": {"moves": ["Flower Trick", "Play Rough", "U-turn", ["Knock Off", "Toxic Spikes"]], "ability": "Protean", "item": "Choice Scarf", "nature": "Jolly", "evs": {"atk": 252, "spd": 4, "spe": 252}, "teratypes": "Grass"}, "Choice Scarf (Grass)": {"moves": ["Flower Trick", "Knock Off", ["Play Rough", "Thunder Punch", "Toxic Spikes"], "U-turn"], "ability": "Protean", "item": "Choice Scarf", "nature": "Jolly", "evs": {"atk": 252, "spd": 4, "spe": 252}}},
  "Skeledirge": {"Physically Defensive (Ghost)": {"moves": ["Torch Song", "Will-O-Wisp", ["Earth Power", "Hex"], "Slack Off"], "ability": "Unaware", "item": "Heavy-Duty Boots", "nature": "Bold", "ivs": {"atk": 0}, "evs": {"hp": 248, "def": 112, "spe": 148}}},
  "Clodsire": {"Specially Defensive (Ground)": {"moves": ["Earthquake", "Poison Jab", ["Toxic Spikes", "Toxic"], "Recover"], "ability": ["Unaware", "Water Absorb"], "item": "Black Sludge", "nature": "Careful", "evs": {"hp": 252, "def": 160, "spd": 96}}},
  "Kingambit": {"Swords Dance (Steel)": {"moves": ["Iron Head", "Sucker Punch", "Knock Off", "Swords Dance"], "ability": "Supreme Overlord", "item": ["Leftovers", "Black Glasses"], "nature": "Adamant", "evs": {"hp": 116, "atk": 252, "spe": 140}}},
  "Great Tusk": {"Utility (Fighting)": {"moves": ["Earthquake", "Knock Off", "Stealth Rock", "Rapid Spin"], "item": "Leftovers", "nature": "Impish", "evs": {"hp": 248, "def": 40, "spe": 220}}, "Choiced Attacker (Fighting)": {"moves": ["Close Combat", "Headlong Rush", "Knock Off", ["Ice Spinner", "Stone Edge", "Rapid Spin"]], "item": ["Choice Band", "Choice Scarf"], "nature": "Jolly", "evs": {"atk": 252, "spd": 4, "spe": 252}}, "Bulk Up (Ground)": {"moves": ["Close Combat", ["Earthquake", "Ice Spinner"], ["Rapid Spin", "Knock Off"], "Bulk Up"], "item": "Fightinium Z", "nature": "Jolly", "evs": {"atk": 252, "spd": 4, "spe": 252}}},
  "Iron Treads": {"Choice Scarf (Ground)": {"moves": ["Earthquake", "Iron Head", ["Ice Spinner", "Knock Off"], ["Stone Edge", "Knock Off"]], "item": "Choice Scarf", "nature": "Jolly", "evs": {"atk": 252, "spd": 4, "spe": 252}}},
  "Iron Hands": {"Assault Vest (Electric)": {"moves": ["Drain Punch", "Ice Punch", ["Rock Slide", "Thunder Punch"], ["Earthquake", "Volt Switch"]], "item": "Assault Vest", "nature": "Careful", "evs": {"hp": 72, "atk": 92, "def": 52, "spd": 248, "spe": 44}}},
  "Ting-Lu": {"Mixed Wall (Dark)": {"moves": ["Earthquake", "Heavy Slam", ["Spikes", "Whirlwind"], ["Stealth Rock", "Whirlwind"]], "item": "Leftovers", "nature": "Impish", "evs": {"hp": 236, "atk": 32, "spd": 240}}, "Physically Defensive (Ground)": {"moves": [["Earthquake", "Throat Chop"], ["Ruination", "Body Press"], ["Spikes", "Stealth Rock"], "Whirlwind"], "item": "Leftovers", "nature": "Impish", "evs": {"hp": 252, "def": 252, "spd": 4}}},
  "Roaring Moon": {"Choice Scarf (Dragon)": {"moves": ["Crunch", "Outrage", ["Iron Head", "Earthquake"], ["U-turn", "Earthquake"]], "item": "Choice Scarf", "nature": "Jolly", "evs": {"atk": 252, "spd": 4, "spe": 252}}},
  "Iron Valiant": {"Swords Dance (Fairy)": {"moves": ["Swords Dance", "Close Combat", "Spirit Break", "Knock Off"], "item": "Fightinium Z", "nature": "Jolly", "evs": {"atk": 252, "spd": 4, "spe": 252}}, "Choice Specs (Fighting)": {"moves": ["Moonblast", ["Psyshock", "Aura Sphere"], ["Thunderbolt", "Energy Ball"], ["Shadow Ball", "Trick"]], "item": "Choice Specs", "nature": "Timid", "evs": {"spa": 252, "spd": 4, "spe": 252}}}
}